{
    "1" : {
        "name" : "Открытка, на день рождения",
        "cost" : 1000,
        "description" : "Открытка с иллюстрацией русалки на песке. <br>размер: 15смх10см <br>Поверхность: глянцевая <br>Сзади: место для подписи и марки</p>",
        "image" : "img/goods.jpg"
    },
    "2" : {
        "name" : "Заколка для волос",
        "cost" : 999,
        "description" : "Открытка с иллюстрацией русалки на песке. <br>размер: 15смх10см <br>Поверхность: глянцевая <br>Сзади: место для подписи и марки</p>",
        "image" : "img/goods.jpg"
    },
    "3" : {
        "name" : "Кофта с принтом",
        "cost" : 10000,
        "description" : "Открытка с иллюстрацией русалки на песке. <br>размер: 15смх10см <br>Поверхность: глянцевая <br>Сзади: место для подписи и марки</p>",
        "image" : "img/goods.jpg"
    },
    "9" : {
        "name" : "Толстовка с принтом",
        "cost" : 10500,
        "description" : "Открытка с иллюстрацией русалки на песке. <br>размер: 15смх10см <br>Поверхность: глянцевая <br>Сзади: место для подписи и марки</p>",
        "image" : "img/goods.jpg"
    }
}